django_pg_stat_statements/__init__.py
django_pg_stat_statements/admin.py
django_pg_stat_statements/apps.py
django_pg_stat_statements/migrations/0001_create_pg_stat_statements_extension.py
django_pg_stat_statements/migrations/0002_create_query_statistic_model.py
django_pg_stat_statements/migrations/__init__.py
django_pg_stat_statements/models.py
django_pg_stat_statements/tests.py
django_pg_stat_statements/utils.py
django_pg_stat_statements-0.1.0.dist-info/LICENSE
django_pg_stat_statements-0.1.0.dist-info/METADATA
django_pg_stat_statements-0.1.0.dist-info/WHEEL
django_pg_stat_statements-0.1.0.dist-info/RECORD
