Metadata-Version: 2.1
Name: django-pg-stat-statements
Version: 0.1.0
Summary: A PostgreSQL profiler for Django that uses pg_stat_statements extension
Author: blag
Requires-Python: >=3.11
Classifier: Environment :: Web Environment
Classifier: Framework :: Django
Classifier: Intended Audience :: Developers
Classifier: License :: OSI Approved :: Apache Software License
Classifier: Operating System :: OS Independent
Classifier: Programming Language :: Python
Classifier: Programming Language :: Python :: 3
Classifier: Programming Language :: Python :: 3.11
Classifier: Programming Language :: Python :: 3.12
Classifier: Programming Language :: Python :: 3.13
Classifier: Programming Language :: Python :: 3.10
Classifier: Programming Language :: Python :: 3.8
Classifier: Programming Language :: Python :: 3.9
Classifier: Topic :: Internet :: WWW/HTTP
Classifier: Topic :: Internet :: WWW/HTTP :: Dynamic Content
Requires-Dist: Django (>=2.2)
Requires-Dist: psycopg2-binary (>=2.9.10)
Project-URL: Homepage, https://github.com/blag/django-pg-stat-statements
